os_bedtime/__init__.py
os_bedtime-0.2.1.dist-info/METADATA
os_bedtime-0.2.1.dist-info/WHEEL
os_bedtime-0.2.1.dist-info/licenses/LICENSE
os_bedtime-0.2.1.dist-info/RECORD
