Metadata-Version: 2.1
Name: os_bedtime
Version: 0.2.1
Summary: Put your computer to sleep, etc.
Project-URL: Homepage, https://github.com/Holandsoest/os_bedtime
Project-URL: Bug Tracker, https://github.com/Holandsoest/os_bedtime/issues
Author-email: Holandsoest <holandsoest@gmail.com>
License-File: LICENSE
Classifier: License :: OSI Approved :: MIT License
Classifier: Operating System :: OS Independent
Classifier: Programming Language :: Python :: 3
Requires-Python: >=3.7
